[{"createdBy":"","modifiedBy":"","createdDate":1592521157716,"modifiedDate":1592521157716,"id":46,"name":"[COVID-19 TEST] Concept Set for Paulina NQ4"},{"createdBy":"","modifiedBy":"","createdDate":1592523936730,"modifiedDate":1592523936730,"id":47,"name":"[COVID-19 TEST] Concept Set for Paulina HF"},{"createdBy":"","modifiedBy":"","createdDate":1592524066222,"modifiedDate":1592524066222,"id":48,"name":"[COVID-19 TEST] Concept Set for Paulina HT"},{"createdBy":"","modifiedBy":"","createdDate":1592343556764,"modifiedDate":1597443654316,"id":42,"name":"[R2D2 - COVID19] HEMOGLOBIN A1C measurement  in blood - NGSP"},{"createdBy":"","modifiedBy":"","createdDate":1592343275493,"modifiedDate":1596995523149,"id":39,"name":"[R2D2 - COVID19] Diabetes Mellitus"},{"createdBy":"","modifiedBy":"","createdDate":1601416402165,"modifiedDate":1601416402166,"id":324,"name":"Hypertension -- BMP"},{"createdBy":"","modifiedBy":"","createdDate":1592343514823,"modifiedDate":1592586966598,"id":41,"name":"[COVID19] HEART DISEASE 1"},{"createdBy":"","modifiedBy":"","createdDate":1592524895449,"modifiedDate":1592587000250,"id":49,"name":"[COVID19] HEART DISEASE 2 (OHDSI Charybdis)"},{"createdBy":"","modifiedBy":"","createdDate":1593128225804,"modifiedDate":1593128225805,"id":69,"name":"[COVID-19 TEST] Mechanical Ventilation - Both Sites - Exclusion"},{"createdBy":"","modifiedBy":"","createdDate":1595223653682,"modifiedDate":1595223704397,"id":210,"name":"R2D2_Question9_ConceptSet_6_5_2020"},{"createdBy":"","modifiedBy":"","createdDate":1594244456681,"modifiedDate":1594245931895,"id":109,"name":"[COVID-19] R2D2 - LOINC Viral Testing"},{"createdBy":"","modifiedBy":"","createdDate":1593118602003,"modifiedDate":1593118811072,"id":52,"name":"[COVID-19 TEST] Mechanical Ventilation - OHDSI Charybdis"},{"createdBy":"larissa_neumann","modifiedBy":"","createdDate":1590510178290,"modifiedDate":1590510178290,"id":1,"name":"[COVID19] DIALYSIS"},{"createdBy":"larissa_neumann","modifiedBy":"","createdDate":1590510247872,"modifiedDate":1590510247872,"id":2,"name":"[COVID19] ACUTE KIDNEY INJURY"},{"createdBy":"larissa_neumann","modifiedBy":"","createdDate":1590510301626,"modifiedDate":1590510301627,"id":3,"name":"[COVID19] DEATH"},{"createdBy":"larissa_neumann","modifiedBy":"","createdDate":1590510366153,"modifiedDate":1590510366154,"id":4,"name":"[COVID19] DIAGNOSIS"},{"createdBy":"larissa_neumann","modifiedBy":"","createdDate":1590510430393,"modifiedDate":1590510430394,"id":5,"name":"[COVID19] MECHANICAL VENTILATION"},{"createdBy":"","modifiedBy":"","createdDate":1593119100048,"modifiedDate":1593119120477,"id":53,"name":"[COVID-19 TEST] Mechanical Ventilation - Addendum"},{"createdBy":"","modifiedBy":"","createdDate":1594775694751,"modifiedDate":1594779255278,"id":158,"name":"copy [COVID-19] N3C - Phenotype Version 1.6 - ICD10CM - Diagnoses which are included in CDC Guidelines"},{"createdBy":"jejo_koola","modifiedBy":"","createdDate":1590601283183,"modifiedDate":1590601283184,"id":8,"name":"[COVID19] TESTING (PRE-COORDINATED MEASUREMENTS EXCLUDED)"},{"createdBy":"jejo_koola","modifiedBy":"","createdDate":1590601169396,"modifiedDate":1590601315268,"id":7,"name":"[COVID19] TESTING (PRE-COORDINATED MEASUREMENTS) POSITIVE"},{"createdBy":"jejo_koola","modifiedBy":"","createdDate":1590601624535,"modifiedDate":1590601624535,"id":9,"name":"[COVID19] INPATIENT VISIT"},{"createdBy":"jejo_koola","modifiedBy":"","createdDate":1590602439621,"modifiedDate":1590602439622,"id":10,"name":"[COVID19] SOURCE CODES"},{"createdBy":"","modifiedBy":"","createdDate":1592612632125,"modifiedDate":1593119298445,"id":50,"name":"[COVID-19 TEST] Mechanical Ventilation - Other Site"},{"createdBy":"jejo_koola","modifiedBy":"","createdDate":1590601084557,"modifiedDate":1591054790005,"id":6,"name":"[OHDSI COVID19] COVID19 associated disease by diagnostic codes, including asymptomatic"},{"createdBy":"","modifiedBy":"","createdDate":1591054072597,"modifiedDate":1591060173662,"id":12,"name":"[COVID19] COVID19 diagnosis by COVID19 specific diagnostic codes"},{"createdBy":"jejo_koola","modifiedBy":"","createdDate":1591036618127,"modifiedDate":1591036675774,"id":11,"name":"[Jejo-Test] Benign Prostatic Hyperplasia"},{"createdBy":"","modifiedBy":"","createdDate":1591371374201,"modifiedDate":1591371374201,"id":35,"name":"[TEST] Myalgia"},{"createdBy":"","modifiedBy":"","createdDate":1592266627886,"modifiedDate":1592266627887,"id":38,"name":"[COVID-19 TEST] CONCEPT SET FOR PAULINA"},{"createdBy":"","modifiedBy":"","createdDate":1594247391800,"modifiedDate":1594247407890,"id":113,"name":"[COVID-19] R2D2 - OMOP only"},{"createdBy":"","modifiedBy":"","createdDate":1594248037143,"modifiedDate":1594248098079,"id":115,"name":"[COVID-19] R2D2 - CPT4/HCPCS"},{"createdBy":"","modifiedBy":"","createdDate":1593120371753,"modifiedDate":1593120723470,"id":58,"name":"[COVID-19 TEST] Mechanical Ventilation - OHDSI CohortDefinition318/conceptset#9"},{"createdBy":"","modifiedBy":"","createdDate":1592440452235,"modifiedDate":1592440452235,"id":43,"name":"[OHDSI Cov19] HIV/AIDS"},{"createdBy":"","modifiedBy":"","createdDate":1592440638888,"modifiedDate":1592440638888,"id":44,"name":"[Covid19-Cohort170] ACE inhibitors"},{"createdBy":"","modifiedBy":"","createdDate":1592440738250,"modifiedDate":1592440738250,"id":45,"name":"[COVID-19 COHORT 179] Angiotensin receptor blockers (ARBs)"},{"createdBy":"","modifiedBy":"","createdDate":1594248023025,"modifiedDate":1594250225873,"id":114,"name":"old #108: [COVID-19] Superset N3C LOINC Viral Testing + N3C SNOMED + LOINC all UC sites  Viral Testing + more LOINC Viral Testing + Measurements of SARSCOV2 without antibody testing"},{"createdBy":"","modifiedBy":"","createdDate":1593646024343,"modifiedDate":1593646285483,"id":88,"name":"[COVID-19] N3C - LOINC Viral Testing"},{"createdBy":"","modifiedBy":"","createdDate":1594246540698,"modifiedDate":1594254114057,"id":112,"name":"[COVID-19] R2D2 - SNOMED"},{"createdBy":"","modifiedBy":"","createdDate":1593168085323,"modifiedDate":1593168085323,"id":73,"name":"most_frequent_MV_OtherSite"},{"createdBy":"","modifiedBy":"","createdDate":1593497046785,"modifiedDate":1594319689375,"id":77,"name":"[COVID19] MECHANICAL VENTILATION -v4 DRAFT"},{"createdBy":"","modifiedBy":"","createdDate":1593123063429,"modifiedDate":1593123063430,"id":66,"name":"[COVID-19 TEST] Mechanical Ventilation - Both Sites - edited"},{"createdBy":"","modifiedBy":"","createdDate":1594320357518,"modifiedDate":1594321280829,"id":121,"name":"ConceptSet_Validation_Charybdis_MechanicalVentilation"},{"createdBy":"","modifiedBy":"","createdDate":1593123177987,"modifiedDate":1593123177988,"id":67,"name":"[COVID-19 TEST] Mechanical Ventilation - Both Sites - combined"},{"createdBy":"","modifiedBy":"","createdDate":1593123506634,"modifiedDate":1593123506635,"id":68,"name":"[COVID-19 TEST] Mechanical Ventilation - Both Sites - edited - and OHDSI cohortdefinition318/conceptset#9"},{"createdBy":"","modifiedBy":"","createdDate":1593218334331,"modifiedDate":1593218453322,"id":74,"name":"[COVID19] MECHANICAL VENTILATION -v2"},{"createdBy":"","modifiedBy":"","createdDate":1594319135351,"modifiedDate":1594327814534,"id":120,"name":"ConceptSet_Validation_Question7_Site10_MechanicalVentilation"},{"createdBy":"","modifiedBy":"","createdDate":1593293248415,"modifiedDate":1593293325458,"id":75,"name":"[COVID19] MECHANICAL VENTILATION -v2 and physical objects"},{"createdBy":"","modifiedBy":"","createdDate":1593129034385,"modifiedDate":1593293482063,"id":70,"name":"[COVID-19] Menchanical Ventilation - Physical Object"},{"createdBy":"","modifiedBy":"","createdDate":1593496812110,"modifiedDate":1593497020008,"id":76,"name":"[COVID19] MECHANICAL VENTILATION -v3 and physical objects, exclude 2 concepts"},{"createdBy":"","modifiedBy":"","createdDate":1593560945473,"modifiedDate":1593560945475,"id":78,"name":"[COVID-19] LOINC FDA approved Viral Testing"},{"createdBy":"","modifiedBy":"","createdDate":1593592622677,"modifiedDate":1593596160501,"id":79,"name":"[COVID-19] LOINC -NOT - FDA approved Viral Testing "},{"createdBy":"","modifiedBy":"","createdDate":1593593321055,"modifiedDate":1593598140580,"id":81,"name":"[COVID-19] LOINC combined - FDA approved and Not FDA approved Viral Testing"},{"createdBy":"","modifiedBy":"","createdDate":1593593112686,"modifiedDate":1593598153061,"id":80,"name":"[COVID-19] LOINC UC sites - Viral Testing"},{"createdBy":"","modifiedBy":"","createdDate":1593621122817,"modifiedDate":1593621122818,"id":82,"name":"QC [COVID-19] LOINC ONLY FDA approved viral testing - From Comparison"},{"createdBy":"","modifiedBy":"","createdDate":1593621160431,"modifiedDate":1593621160432,"id":83,"name":"QC [COVID-19] LOINC ONLY - NOT - FDA approved viral testing - From Comparison"},{"createdBy":"","modifiedBy":"","createdDate":1593621188698,"modifiedDate":1593621221128,"id":84,"name":"QC [COVID-19] LOINC Both FDA approved and NOT FDA approved viral testing - From Comparison"},{"createdBy":"","modifiedBy":"","createdDate":1593621475546,"modifiedDate":1593621475547,"id":85,"name":"QC [COVID-19] LOINC UCSD viral testing"},{"createdBy":"","modifiedBy":"","createdDate":1593621576088,"modifiedDate":1593621576088,"id":86,"name":"QC [COVID-19] LOINC other UC sites viral testing - From Comparison"},{"createdBy":"","modifiedBy":"","createdDate":1593646016610,"modifiedDate":1593646016611,"id":87,"name":"[COVID-19] N3C - LOINC COVID19 Tests"},{"createdBy":"","modifiedBy":"","createdDate":1593646171284,"modifiedDate":1593646298825,"id":89,"name":"QC [COVID-19] N3C only - LOINC Viral Testing - From Comparison"},{"createdBy":"","modifiedBy":"","createdDate":1593648707962,"modifiedDate":1593648707963,"id":90,"name":"[COVID-19] N3C - ICD10CM - Diagnoses"},{"createdBy":"","modifiedBy":"","createdDate":1593649230698,"modifiedDate":1593649230699,"id":91,"name":"[COVID-19] N3C - HCPCS and CPT Code"},{"createdBy":"","modifiedBy":"","createdDate":1593649641203,"modifiedDate":1593649641204,"id":92,"name":"[COVID-19] N3C - SNOMED"},{"createdBy":"","modifiedBy":"","createdDate":1593650082933,"modifiedDate":1593650082933,"id":93,"name":"[COVID-19] N3C - OMOP only"},{"createdBy":"","modifiedBy":"","createdDate":1593650680481,"modifiedDate":1593650733778,"id":98,"name":"[COVID-19] N3C - ALL (LOINC, ICD10CM, HCPCS/CPT, SNOMED, OMOPonly)"},{"createdBy":"","modifiedBy":"","createdDate":1593650838405,"modifiedDate":1593650926328,"id":99,"name":"QC [COVID-19] N3C - (ICD10CM, HCPCS/CPT, SNOMED, OMOPonly - LOINC excluded)"},{"createdBy":"","modifiedBy":"","createdDate":1593810861702,"modifiedDate":1593810861702,"id":100,"name":"Hypertension"},{"createdBy":"","modifiedBy":"","createdDate":1594075647303,"modifiedDate":1594075647304,"id":101,"name":"Lopez COVID Positive Admitted Cardiovascular Injury"},{"createdBy":"","modifiedBy":"","createdDate":1594154838610,"modifiedDate":1594154905000,"id":102,"name":"[COVID-19] N3C - ICD10CM - Diagnoses - only SARSCOV2 related"},{"createdBy":"","modifiedBy":"","createdDate":1594154981595,"modifiedDate":1594154981596,"id":103,"name":"[COVID-19] Superset N3C LOINC Viral Testing + N3C SNOMED"},{"createdBy":"","modifiedBy":"","createdDate":1594155110869,"modifiedDate":1594155110869,"id":104,"name":"[COVID-19] Superset N3C LOINC Viral Testing + N3C SNOMED + LOINC all UC sites  Viral Testing"},{"createdBy":"","modifiedBy":"","createdDate":1594155136956,"modifiedDate":1594155271145,"id":105,"name":"[COVID-19] Superset N3C LOINC Viral Testing + N3C SNOMED + LOINC all UC sites  Viral Testing + more LOINC Viral Testing"},{"createdBy":"","modifiedBy":"","createdDate":1594155417180,"modifiedDate":1594155709717,"id":106,"name":"[COVID-19] Measurement of Severe acute respiratory syndrome coronavirus 2 (SARS-CoV-2) without antibody testing"},{"createdBy":"","modifiedBy":"","createdDate":1594155943438,"modifiedDate":1594155959365,"id":107,"name":"[COVID-19] Measurement of Severe acute respiratory syndrome coronavirus 2 (SARS-CoV-2) without antibody testing + N3C LOINC Viral Testing"},{"createdBy":"","modifiedBy":"","createdDate":1602087941635,"modifiedDate":1602087941636,"id":325,"name":"mammogram"},{"createdBy":"","modifiedBy":"","createdDate":1594327799063,"modifiedDate":1594327799063,"id":123,"name":"ConceptSet_Validation_Question7_Site11_MechanicalVentilation"},{"createdBy":"","modifiedBy":"","createdDate":1594321323708,"modifiedDate":1594329744812,"id":122,"name":"[COVID19] R2D2 - MECHANICAL VENTILATION - Version 1.1"},{"createdBy":"","modifiedBy":"","createdDate":1594333324806,"modifiedDate":1594333324807,"id":124,"name":"R2D2_Question1_ConceptSet_6_10_2020"},{"createdBy":"","modifiedBy":"","createdDate":1594333528269,"modifiedDate":1594333528269,"id":125,"name":"R2D2_Question2_ConceptSet_6_11_2020"},{"createdBy":"","modifiedBy":"","createdDate":1594333582007,"modifiedDate":1594333582008,"id":126,"name":"R2D2_Question3_ConceptSet_6_11_2020"},{"createdBy":"","modifiedBy":"","createdDate":1603327423353,"modifiedDate":1603327423354,"id":328,"name":"Full Term Delivery"},{"createdBy":"","modifiedBy":"","createdDate":1594333677927,"modifiedDate":1594333773035,"id":127,"name":"[COVID-19] R2D2 - Serum Creatinine"},{"createdBy":"","modifiedBy":"","createdDate":1594771161765,"modifiedDate":1594771201502,"id":156,"name":"[COVID-19] Superset - N3C - Phenotype Version 1.6 - ALL but no LOINC antibody tests and no CPT antibody test (included LOINC COVID19 Tests only viral tests and SNOMED and HCPCS/CPT4 and ICD10CM and OMOP Extension)"},{"createdBy":"","modifiedBy":"","createdDate":1594245953910,"modifiedDate":1594366027355,"id":111,"name":"[COVID-19] R2D2 - ICD10CM - COVID-19, SARS-associated coronavirus or coronavirus infection/diagnoses"},{"createdBy":"","modifiedBy":"","createdDate":1594670250907,"modifiedDate":1594670297583,"id":128,"name":"R2D2_Question4_ConceptSet_6_2_2020"},{"createdBy":"","modifiedBy":"","createdDate":1594670860788,"modifiedDate":1594670860788,"id":129,"name":"R2D2_Question5_ConceptSet_6_11_2020"},{"createdBy":"","modifiedBy":"","createdDate":1595223759783,"modifiedDate":1595223759783,"id":211,"name":"R2D2_Question10_ConceptSet_6_5_2020"},{"createdBy":"","modifiedBy":"","createdDate":1594761645832,"modifiedDate":1594762639484,"id":144,"name":"N3C - Phenotype Version 1.6 - LOINC COVID19 Tests only viral tests"},{"createdBy":"","modifiedBy":"","createdDate":1594762398740,"modifiedDate":1594762859970,"id":149,"name":"[COVID-19] Superset - N3C - Phenotype Version 1.6 - ALL but no LOINC antibody tests (included LOINC COVID19 Tests only viral tests and SNOMED and HCPCS/CPT4 and ICD10CM and OMOP Extension)"},{"createdBy":"","modifiedBy":"","createdDate":1594698305916,"modifiedDate":1594753401774,"id":131,"name":" [COVID-19] N3C - Phenotype Version 1.6 - ICD10CM - Diagnoses"},{"createdBy":"","modifiedBy":"","createdDate":1594777396691,"modifiedDate":1594777446204,"id":164,"name":"R2D2 - ICD10CM Guidelines - Other Bronchitis- 1) Before April 1st, 2020"},{"createdBy":"","modifiedBy":"","createdDate":1594753693982,"modifiedDate":1594753706491,"id":132,"name":"[COVID-19] N3C - Phenotype Version 1.6 - HCPCS and CPT Code"},{"createdBy":"","modifiedBy":"","createdDate":1594754133020,"modifiedDate":1594754513098,"id":133,"name":"[COVID-19] N3C - Phenotype Version 1.6 - SNOMED"},{"createdBy":"","modifiedBy":"","createdDate":1594248236871,"modifiedDate":1594776691816,"id":118,"name":"[COVID-19] R2D2 - Phenotype Inclusion Criteria - Version 1.0"},{"createdBy":"","modifiedBy":"","createdDate":1594755167085,"modifiedDate":1594755188487,"id":134,"name":"[COVID-19] N3C - Phenotype Version 1.6 - OMOP Extension"},{"createdBy":"","modifiedBy":"","createdDate":1594686389652,"modifiedDate":1594755458463,"id":130,"name":"[COVID-19] N3C - Phenotype Version 1.6 - LOINC COVID19 Tests"},{"createdBy":"","modifiedBy":"","createdDate":1594771878022,"modifiedDate":1594776701581,"id":157,"name":"[COVID-19] R2D2 - Phenotype Inclusion Criteria - Version 1.1"},{"createdBy":"","modifiedBy":"","createdDate":1594755605111,"modifiedDate":1594757658826,"id":138,"name":"[COVID-19] Superset  - N3C - Phenotype Version 1.6 - ALL which could be imported (LOINC, ICD10CM, HCPCS/CPT4, SNOMED, OMOP Extension)"},{"createdBy":"","modifiedBy":"","createdDate":1594775699825,"modifiedDate":1594776945804,"id":159,"name":"R2D2 - ICD10CM Guidelines - Pneumonia - 1) Before April 1st, 2020"},{"createdBy":"","modifiedBy":"","createdDate":1594757864940,"modifiedDate":1594758011640,"id":139,"name":"[COVID-19] N3C - Phenotype Version 1.6 - ICD10CM - Diagnoses which are included in CDC Guidelines"},{"createdBy":"","modifiedBy":"","createdDate":1594776736588,"modifiedDate":1594777000897,"id":160,"name":"R2D2 - ICD10CM Guidelines - Pneumonia - 2) After April 1st, 2020"},{"createdBy":"","modifiedBy":"","createdDate":1594755491211,"modifiedDate":1594758898420,"id":135,"name":"N3C - Phenotype Version 1.6 - LOINC and ICD10CM"},{"createdBy":"","modifiedBy":"","createdDate":1594755512538,"modifiedDate":1594758906122,"id":136,"name":"N3C - Phenotype Version 1.6 - LOINC and ICD10CM and HCPCS/CPT4"},{"createdBy":"","modifiedBy":"","createdDate":1594755528354,"modifiedDate":1594758914851,"id":137,"name":"N3C - Phenotype Version 1.6 - LOINC and ICD10CM and HCPCS/CPT4 and SNOMED"},{"createdBy":"","modifiedBy":"","createdDate":1594777049427,"modifiedDate":1594777139884,"id":162,"name":"R2D2 - ICD10CM Guidelines - Acute Bronchitis- 1) Before April 1st, 2020"},{"createdBy":"","modifiedBy":"","createdDate":1594766440085,"modifiedDate":1594769793935,"id":150,"name":"N3C - Phenotype Version 1.6 - ALL but no LOINC antibody tests and only ICD10CM CDC Guidelines (included LOINC COVID19 Tests only viral tests and SNOMED and HCPCS/CPT4 and ICD10CM only CDC mentioned codes and OMOP Extension)"},{"createdBy":"","modifiedBy":"","createdDate":1594777284357,"modifiedDate":1594777392811,"id":163,"name":"R2D2 - ICD10CM Guidelines - Acute Bronchitis - 2) After April 1st, 2020"},{"createdBy":"","modifiedBy":"","createdDate":1594758868230,"modifiedDate":1594759212016,"id":141,"name":"N3C - Phenotype Version 1.6 - ICD10CM and SNOMED"},{"createdBy":"","modifiedBy":"","createdDate":1594758922946,"modifiedDate":1594759221697,"id":142,"name":"N3C - Phenotype Version 1.6 - ICD10CM and SNOMED - Strong Positive"},{"createdBy":"","modifiedBy":"","createdDate":1594759195446,"modifiedDate":1594759230015,"id":143,"name":"N3C - Phenotype Version 1.6 - ICD10CM and SNOMED - Weak Positive"},{"createdBy":"","modifiedBy":"","createdDate":1594777448378,"modifiedDate":1594777521823,"id":165,"name":"R2D2 - ICD10CM Guidelines - Other Bronchitis- 2) After April 1st, 2020"},{"createdBy":"","modifiedBy":"","createdDate":1594762186747,"modifiedDate":1594762186748,"id":145,"name":"N3C - Phenotype Version 1.6 - LOINC COVID19 Tests - antibody tests"},{"createdBy":"","modifiedBy":"","createdDate":1594762280042,"modifiedDate":1594762280043,"id":146,"name":"N3C - Phenotype Version 1.6 - LOINC COVID19 Tests - only viral tests and SNOMED"},{"createdBy":"","modifiedBy":"","createdDate":1594762304738,"modifiedDate":1594762304738,"id":147,"name":"N3C - Phenotype Version 1.6 - LOINC COVID19 Tests - only viral tests and SNOMED and HCPCS/CPT4"},{"createdBy":"","modifiedBy":"","createdDate":1594762331527,"modifiedDate":1594762331528,"id":148,"name":"N3C - Phenotype Version 1.6 - LOINC COVID19 Tests - only viral tests and SNOMED and HCPCS/CPT4 and ICD10CM"},{"createdBy":"","modifiedBy":"","createdDate":1594777553237,"modifiedDate":1594777724689,"id":166,"name":"R2D2 - ICD10CM Guidelines - Lower Respiratory Infection - 1) Before April 1st, 2020"},{"createdBy":"","modifiedBy":"","createdDate":1594769930448,"modifiedDate":1594769930449,"id":151,"name":"Concept Ids included in 118 and not in 150"},{"createdBy":"","modifiedBy":"","createdDate":1594777726130,"modifiedDate":1594777780505,"id":167,"name":"R2D2 - ICD10CM Guidelines - Lower Respiratory Infection - 2) After April 1st, 2020"},{"createdBy":"","modifiedBy":"","createdDate":1594769951984,"modifiedDate":1594770219664,"id":152,"name":"Concept Ids should be added to new proposed method while creating a new R2D2 concept set (similar to 118)"},{"createdBy":"","modifiedBy":"","createdDate":1594778024574,"modifiedDate":1594778143041,"id":170,"name":"R2D2 - ICD10CM Guidelines - Respiratory Infection - 1) Before April 1st, 2020"},{"createdBy":"","modifiedBy":"","createdDate":1594778145039,"modifiedDate":1594778182608,"id":171,"name":"R2D2 - ICD10CM Guidelines - Respiratory Infection - 2) After April 1st, 2020"},{"createdBy":"","modifiedBy":"","createdDate":1594777802553,"modifiedDate":1594778240471,"id":168,"name":"R2D2 - ICD10CM Guidelines - ARDS - 1) Before April 1st, 2020"},{"createdBy":"","modifiedBy":"","createdDate":1594777960139,"modifiedDate":1594778249699,"id":169,"name":"R2D2 - ICD10CM Guidelines - ARDS - 2) After April 1st, 2020"},{"createdBy":"","modifiedBy":"","createdDate":1594778329755,"modifiedDate":1594778557524,"id":173,"name":"Not N3C - R2D2 - ICD10CM Guidelines - Concerned Exposure to COVID-19 - 2) After April 1st, 2020"},{"createdBy":"","modifiedBy":"","createdDate":1594778256295,"modifiedDate":1594778548572,"id":172,"name":"Not N3C - R2D2 - ICD10CM Guidelines - Concerned Exposure to COVID-19 - 1) Before April 1st, 2020"},{"createdBy":"","modifiedBy":"","createdDate":1594778564905,"modifiedDate":1594778666205,"id":174,"name":"R2D2 - ICD10CM Guidelines - Actual Exposure to COVID-19 - 1) Before April 1st, 2020"},{"createdBy":"","modifiedBy":"","createdDate":1594778667963,"modifiedDate":1594778866449,"id":175,"name":"R2D2 - ICD10CM Guidelines - Actual Exposure to COVID-19 - 2) After April 1st, 2020"},{"createdBy":"","modifiedBy":"","createdDate":1594778967299,"modifiedDate":1594778967300,"id":176,"name":"R2D2 - ICD10CM Guidelines - Signs and symptoms without definitive diagnosis of COVID-19 - 1) Before April 1st, 2020 and 2) After April 1st, 2020"},{"createdBy":"","modifiedBy":"","createdDate":1594829359226,"modifiedDate":1594829467933,"id":179,"name":"R2D2 - Phenotype Inclusion Criteria - Version 1.1 - OMOP Extension"},{"createdBy":"","modifiedBy":"","createdDate":1594828933589,"modifiedDate":1594829080209,"id":177,"name":"R2D2 - Phenotype Inclusion Criteria - Version 1.1 - LOINC"},{"createdBy":"","modifiedBy":"","createdDate":1594829057606,"modifiedDate":1594829167061,"id":178,"name":"R2D2 - Phenotype Inclusion Criteria - Version 1.1 - SNOMED"},{"createdBy":"","modifiedBy":"","createdDate":1594829475301,"modifiedDate":1594829502549,"id":180,"name":"R2D2 - Phenotype Inclusion Criteria - Version 1.1 - ICD10CM"},{"createdBy":"","modifiedBy":"","createdDate":1594829559886,"modifiedDate":1594829593840,"id":181,"name":"R2D2 - Phenotype Inclusion Criteria - Version 1.1 - HCPCS/CPT4"},{"createdBy":"","modifiedBy":"","createdDate":1594857850578,"modifiedDate":1594857910403,"id":199,"name":"COPY OF #157 (#157 created on July 14,2020): [COVID-19] R2D2 - Phenotype Inclusion Criteria - Version 1.1"},{"createdBy":"","modifiedBy":"","createdDate":1594858217844,"modifiedDate":1594858514353,"id":200,"name":"N3C - Phenotype Version 1.6 - LOINC addendum (import not possible on July13/14, but on July15,2020)"},{"createdBy":"","modifiedBy":"","createdDate":1594858525440,"modifiedDate":1594858571155,"id":202,"name":"N3C - Phenotype Version 1.6 - LOINC addendum only viral tests (import not possible on July13/14, but on July15,2020)"},{"createdBy":"","modifiedBy":"","createdDate":1594858377910,"modifiedDate":1594858477381,"id":201,"name":"COPY OF #156 (created on July14, 2020) [COVID-19] Superset - N3C - Phenotype Version 1.6 - ALL but no LOINC antibody tests and no CPT antibody test (included LOINC COVID19 Tests only viral tests and SNOMED and HCPCS/CPT4 and ICD10CM and OMOP Extension)"},{"createdBy":"","modifiedBy":"","createdDate":1595554121194,"modifiedDate":1595575835319,"id":244,"name":"[R2D2 - COVID19] INPATIENT VISIT"},{"createdBy":"","modifiedBy":"","createdDate":1595553873057,"modifiedDate":1595634817571,"id":242,"name":"[R2D2 - COVID19]  SARSCOV2 Viral Lab Test (pre-coordinated measurements excluded)"},{"createdBy":"","modifiedBy":"","createdDate":1595869103685,"modifiedDate":1595869276060,"id":250,"name":"[R2D2 - COVID19] - antibody tests"},{"createdBy":"","modifiedBy":"","createdDate":1594944435973,"modifiedDate":1594944435973,"id":208,"name":"QC D-Dimer"},{"createdBy":"","modifiedBy":"","createdDate":1596764147874,"modifiedDate":1597944485924,"id":256,"name":"[R2D2 COVID-19] Discharged Home - all"},{"createdBy":"","modifiedBy":"","createdDate":1603325764965,"modifiedDate":1603325764966,"id":326,"name":"Screening Mammogram"},{"createdBy":"","modifiedBy":"","createdDate":1597094179760,"modifiedDate":1597719678056,"id":281,"name":"Invasive Mechanical Ventilation/Intubation of Respiratory Tract - ALL"},{"createdBy":"","modifiedBy":"","createdDate":1597711534738,"modifiedDate":1597719703832,"id":288,"name":"Invasive Mechanical Ventilation - Date/Datetime"},{"createdBy":"","modifiedBy":"","createdDate":1597947947525,"modifiedDate":1597949433528,"id":305,"name":"[R2D2 - COVID19] Smoking - Meas Value - Never Smoker"},{"createdBy":"","modifiedBy":"","createdDate":1597789562824,"modifiedDate":1597789579504,"id":292,"name":"[R2D2 GLORE] Race - White"},{"createdBy":"","modifiedBy":"","createdDate":1596821435946,"modifiedDate":1596917868878,"id":262,"name":"[R2D2 COVID-19] Coronary Heart Disease (Coronary Artery Disease, Angina  pectoris, Myocardial Ischemia/Infarction, Ischemic Heart Disease)"},{"createdBy":"","modifiedBy":"","createdDate":1595362252332,"modifiedDate":1595362273923,"id":217,"name":"R2D2 - Phenotype Inclusion Criteria - Version 1.2 - ICD10CM - Before April 1st, 2020"},{"createdBy":"","modifiedBy":"","createdDate":1596919749751,"modifiedDate":1596919749751,"id":265,"name":"COPY OF: [COVID19] DIABETES MELLITUS"},{"createdBy":"","modifiedBy":"","createdDate":1595458453112,"modifiedDate":1595459172994,"id":234,"name":"old: R2D2 - Phenotype Inclusion Criteria - Version 1.2 - COVID19 Diagnosis - no LOGIC - July 21, 2020"},{"createdBy":"","modifiedBy":"","createdDate":1595458823482,"modifiedDate":1595459191226,"id":236,"name":"old: R2D2 - Phenotype Inclusion Criteria - Version 1.2 - COVID19 Diagnosis - all with LOGIC - July 21, 2020"},{"createdBy":"","modifiedBy":"","createdDate":1595455145389,"modifiedDate":1595459223327,"id":232,"name":"old: R2D2 - Phenotype Inclusion Criteria - Version 1.2 - created on July 15th/16th 2020 - July 21, 2020"},{"createdBy":"","modifiedBy":"","createdDate":1595359049022,"modifiedDate":1595459260571,"id":215,"name":"old: R2D2 - Phenotype Inclusion Criteria - Version 1.2 - created on July 15th/16th 2020 - last update July20"},{"createdBy":"","modifiedBy":"","createdDate":1596766069370,"modifiedDate":1596771173154,"id":258,"name":"[R2D2] Deceased status - inpatient visit"},{"createdBy":"","modifiedBy":"","createdDate":1604432450072,"modifiedDate":1604440185419,"id":329,"name":"[R2D2 - COVID19] Smoker - Smoking/ Nicotine Dependence - excl. e-cigarettes, other forms of tobacco"},{"createdBy":"","modifiedBy":"","createdDate":1596171899772,"modifiedDate":1596771565389,"id":253,"name":"[R2D2] Deceased status - without specified location"},{"createdBy":"","modifiedBy":"","createdDate":1594859000846,"modifiedDate":1595459631836,"id":204,"name":"[COVID-19] R2D2 - Phenotype Inclusion Criteria - Version 1.2 - created on July 15th/16th 2020 - last update July 22, 2020"},{"createdBy":"","modifiedBy":"","createdDate":1595365005748,"modifiedDate":1595459741906,"id":224,"name":"[COVID-19] R2D2 - Phenotype Inclusion Criteria - Version 1.2 - COVID19 Diagnosis - all without LOGIC - last update July 22, 2020"},{"createdBy":"","modifiedBy":"","createdDate":1612201498010,"modifiedDate":1612201701981,"id":331,"name":"Lumpectomy"},{"createdBy":"","modifiedBy":"","createdDate":1596820037958,"modifiedDate":1596820175531,"id":260,"name":"[R2D2] Deceased status - ALL"},{"createdBy":"","modifiedBy":"","createdDate":1597104733408,"modifiedDate":1597104754545,"id":284,"name":"[R2D2 GLORE] Gender - unknown"},{"createdBy":"","modifiedBy":"","createdDate":1595446177252,"modifiedDate":1595459752390,"id":231,"name":"[COVID-19] R2D2 - Phenotype Inclusion Criteria - Version 1.2 - COVID19 Diagnosis - all with LOGIC - last update July 22, 2020"},{"createdBy":"","modifiedBy":"","createdDate":1596996505500,"modifiedDate":1597443441869,"id":279,"name":"[R2D2 - COVID19] HEMOGLOBIN A1C measurement  in blood - IFCC"},{"createdBy":"","modifiedBy":"","createdDate":1595373394226,"modifiedDate":1595459811503,"id":228,"name":"[COVID-19] R2D2 - Phenotype Inclusion Criteria - Version 1.2 - COVID19 Diagnoses ICD10CM and mapped SNOMED - with LOGIC - last update July 21, 2020"},{"createdBy":"","modifiedBy":"","createdDate":1595372900056,"modifiedDate":1595459853426,"id":226,"name":"[COVID-19] R2D2 - Phenotype Inclusion Criteria - Version 1.2 - COVID19 Diagnosis ICD10CM U07.1 and mapped SNOMED code - with LOGIC - last update July 21, 2020"},{"createdBy":"","modifiedBy":"","createdDate":1596932513481,"modifiedDate":1596932855276,"id":267,"name":"[R2D2 - COVID19] Readmission VISIT concepts"},{"createdBy":"","modifiedBy":"","createdDate":1597699323582,"modifiedDate":1597699352855,"id":286,"name":"[R2D2 - COVID19] HEMOGLOBIN A1C measurement  in blood - units"},{"createdBy":"","modifiedBy":"","createdDate":1595533110794,"modifiedDate":1595554451704,"id":240,"name":"[R2D2 - COVID19] Measurement value_as_concept positive/detected/present"},{"createdBy":"","modifiedBy":"","createdDate":1597947196118,"modifiedDate":1597950389730,"id":300,"name":"[R2D2 - COVID19] Smoker - amount smoked"},{"createdBy":"","modifiedBy":"","createdDate":1595554676452,"modifiedDate":1595554811604,"id":246,"name":"[R2D2 -  COVID19] Diagnoses Codes: ICD10CM U07.1 and mapped SNOMED 840539006- with LOGIC - after April 1, 2020"},{"createdBy":"","modifiedBy":"","createdDate":1595555249809,"modifiedDate":1595555283278,"id":248,"name":"[R2D2 - COVID19] Diagnoses Codes: all without logic"},{"createdBy":"","modifiedBy":"","createdDate":1596947787338,"modifiedDate":1596947849551,"id":271,"name":"[R2D2 GLORE] Race - Black"},{"createdBy":"","modifiedBy":"","createdDate":1596947378082,"modifiedDate":1596947862650,"id":269,"name":"[R2D2 GLORE] Gender - Female"},{"createdBy":"","modifiedBy":"","createdDate":1596948442647,"modifiedDate":1596948442647,"id":273,"name":"[R2D2 GLORE] Ethnicity - Hispanic or Latino"},{"createdBy":"","modifiedBy":"","createdDate":1597941178143,"modifiedDate":1597950619294,"id":298,"name":"[R2D2 - COVID19] Smoker - Smoking Cessation"},{"createdBy":"","modifiedBy":"","createdDate":1597910168235,"modifiedDate":1597950830476,"id":297,"name":"[R2D2 - COVID19] Smoker - Status Unkown"},{"createdBy":"","modifiedBy":"","createdDate":1596948955579,"modifiedDate":1597047794121,"id":275,"name":"[R2D2 GLORE] Race - Other"},{"createdBy":"","modifiedBy":"","createdDate":1596905769082,"modifiedDate":1597947341364,"id":264,"name":"old - Smoking (current and ex-smoker)"},{"createdBy":"","modifiedBy":"","createdDate":1597949941808,"modifiedDate":1597954660316,"id":308,"name":"[R2D2 - COVID19] Smoking Status"},{"createdBy":"","modifiedBy":"","createdDate":1598038236441,"modifiedDate":1598038236442,"id":310,"name":"Site12 - ECMO concept set"},{"createdBy":"","modifiedBy":"","createdDate":1597947721879,"modifiedDate":1597947821898,"id":303,"name":"[R2D2 - COVID19] Smoking - Meas Value - Ex-Smoker"},{"createdBy":"","modifiedBy":"","createdDate":1597909685171,"modifiedDate":1597948229653,"id":294,"name":"[R2D2 - COVID19] Ex-Smoker"},{"createdBy":"","modifiedBy":"","createdDate":1598038412685,"modifiedDate":1598039417944,"id":312,"name":"ECMO - Site12 - and OHDSI studies (Charybdis, Cohortdefinition308) - and Site09"},{"createdBy":"","modifiedBy":"","createdDate":1598039820922,"modifiedDate":1598040068809,"id":314,"name":"ECMO - Meas Value - Yes/ECMO"},{"createdBy":"","modifiedBy":"","createdDate":1598989412414,"modifiedDate":1598989412414,"id":316,"name":"old: Hemoglobin A1C version1"},{"createdBy":"","modifiedBy":"","createdDate":1599112267879,"modifiedDate":1599112298457,"id":318,"name":"test_import"},{"createdBy":"","modifiedBy":"","createdDate":1599767615032,"modifiedDate":1599767615033,"id":320,"name":"import_conceptId_262"},{"createdBy":"","modifiedBy":"","createdDate":1594858578542,"modifiedDate":1594858594298,"id":203,"name":"N3C - Phenotype Version 1.6 - LOINC addendum antibody tests (import not possible on July13/14, but on July15,2020)"},{"createdBy":"","modifiedBy":"","createdDate":1594927402251,"modifiedDate":1594927747384,"id":205,"name":"R2D2 Q0019 Glucocorticoids"},{"createdBy":"","modifiedBy":"","createdDate":1595553995102,"modifiedDate":1595635063784,"id":243,"name":"[R2D2 - COVID19] SARSCOV2 Viral Lab Test (pre-coordinated measurements) positive"},{"createdBy":"","modifiedBy":"","createdDate":1596141835495,"modifiedDate":1596141835495,"id":251,"name":"diabetes mellitus"},{"createdBy":"","modifiedBy":"","createdDate":1595455468580,"modifiedDate":1595455468581,"id":233,"name":"QC - add to concept set 204?"},{"createdBy":"","modifiedBy":"","createdDate":1603326578651,"modifiedDate":1603326578652,"id":327,"name":"Mastectomy"},{"createdBy":"","modifiedBy":"","createdDate":1596764534044,"modifiedDate":1596764534045,"id":257,"name":"[R2D2] Discharge Home - UCSD"},{"createdBy":"","modifiedBy":"","createdDate":1604620513760,"modifiedDate":1604620513761,"id":330,"name":"[R2D2 - COVID19] Diabetes Mellitus - #39 and concept_id 4196141\tArthropathy due to type 2 diabetes mellitus"},{"createdBy":"","modifiedBy":"","createdDate":1612383493542,"modifiedDate":1612383493543,"id":332,"name":"Alzheimer Conditions"},{"createdBy":"","modifiedBy":"","createdDate":1597443686046,"modifiedDate":1597444023881,"id":285,"name":"[R2D2 - COVID19] HEMOGLOBIN A1C measurement in blood  - Clinical Observation"},{"createdBy":"","modifiedBy":"","createdDate":1595362279588,"modifiedDate":1595362339114,"id":218,"name":"R2D2 - Phenotype Inclusion Criteria - Version 1.2 - ICD10CM - After April 1st, 2020"},{"createdBy":"","modifiedBy":"","createdDate":1595458788532,"modifiedDate":1595459181805,"id":235,"name":"old: R2D2 - Phenotype Inclusion Criteria - Version 1.2 - COVID19 Diagnosis - ALL -  July 21, 2020"},{"createdBy":"","modifiedBy":"","createdDate":1594939504623,"modifiedDate":1595459293975,"id":207,"name":"old: R2D2 - Phenotype Inclusion Criteria - Version 1.2 - LOINC"},{"createdBy":"","modifiedBy":"","createdDate":1597104604009,"modifiedDate":1597711626289,"id":283,"name":"Observation - value_as_concept - invasive/mechanical ventilation"},{"createdBy":"","modifiedBy":"","createdDate":1595446004458,"modifiedDate":1595459712961,"id":230,"name":"[COVID-19] R2D2 - Phenotype Inclusion Criteria - Version 1.2 - COVID19 Diagnosis - ALL - last update July 22, 2020"},{"createdBy":"","modifiedBy":"","createdDate":1595459571933,"modifiedDate":1595459839997,"id":239,"name":"[COVID19] R2D2 - Phenotype Inclusion Criteria - Version 1.2 - COVID19 Diagnosis ICD10CM B97.29 and mapped SNOMED code - with LOGIC - last update July 21, 2020"},{"createdBy":"","modifiedBy":"","createdDate":1595364602010,"modifiedDate":1595534445660,"id":220,"name":"[COVID-19] R2D2 - Phenotype Inclusion Criteria - Version 1.2 - COVID-19 Viral Lab Test Codes - last update July 23, 2020"},{"createdBy":"","modifiedBy":"","createdDate":1595362159048,"modifiedDate":1595372937440,"id":216,"name":"R2D2 - Phenotype Inclusion Criteria - Version 1.2 - Diagnoses ICD10CM and mapped SNOMED"},{"createdBy":"","modifiedBy":"","createdDate":1595373118980,"modifiedDate":1595373118981,"id":227,"name":"R2D2 - Phenotype Inclusion Criteria - Diagnoses Codes mapped SNOMED codes for included ICD10CM"},{"createdBy":"","modifiedBy":"","createdDate":1595551195329,"modifiedDate":1595551469071,"id":241,"name":"Any Valid Visit"},{"createdBy":"","modifiedBy":"","createdDate":1597852790278,"modifiedDate":1597948099693,"id":293,"name":"old - Values for Smoking Status"},{"createdBy":"","modifiedBy":"","createdDate":1595403372823,"modifiedDate":1595403372823,"id":229,"name":"COPY OF: [COVID19] MECHANICAL VENTILATION"},{"createdBy":"","modifiedBy":"","createdDate":1597706164787,"modifiedDate":1597719694659,"id":287,"name":"Mechanical Ventilation  - Site12"},{"createdBy":"","modifiedBy":"","createdDate":1596947051724,"modifiedDate":1596947131093,"id":268,"name":"[R2D2 GLORE] Gender - Male"},{"createdBy":"","modifiedBy":"","createdDate":1596947604294,"modifiedDate":1596947856873,"id":270,"name":"[R2D2 GLORE] Race - Asian"},{"createdBy":"","modifiedBy":"","createdDate":1596948033022,"modifiedDate":1596948033023,"id":272,"name":"[R2D2 GLORE] Race Native Hawaiian or Pacific Islander"},{"createdBy":"","modifiedBy":"","createdDate":1596948560840,"modifiedDate":1596948560840,"id":274,"name":"[R2D2 GLORE] Race - American Indian or Alaska Native"},{"createdBy":"","modifiedBy":"","createdDate":1595554608226,"modifiedDate":1595554804950,"id":245,"name":"[R2D2 - COVID19] Diagnoses Codes: ICD10CM B97.29 and mapped SNOMED 27619001 - with LOGIC - before April 1, 2020"},{"createdBy":"","modifiedBy":"","createdDate":1595554784883,"modifiedDate":1595554952991,"id":247,"name":"[R2D2 - COVID19] Diagnoses Codes: ICD10CM and mapped SNOMED - with LOGIC - before or/and after April 1, 2020"},{"createdBy":"","modifiedBy":"","createdDate":1597089859332,"modifiedDate":1597090244721,"id":280,"name":"[R2D2] Post-acute care"},{"createdBy":"","modifiedBy":"","createdDate":1597098817777,"modifiedDate":1597098817778,"id":282,"name":"Missing from Charybdis - Mechanical Ventilation"},{"createdBy":"","modifiedBy":"","createdDate":1597909933550,"modifiedDate":1597948248306,"id":295,"name":"[R2D2 - COVID19] Passive Smoker"},{"createdBy":"","modifiedBy":"","createdDate":1597910011444,"modifiedDate":1597948274037,"id":296,"name":"[R2D2 - COVID19] Never Smoker/ Non-Smoker"},{"createdBy":"larissa_neumann","modifiedBy":"","createdDate":1591065019883,"modifiedDate":1597950221898,"id":13,"name":"[R2D2 - COVID19] Smoker - Smoking/ Nicotine Dependence"},{"createdBy":"","modifiedBy":"","createdDate":1597947159575,"modifiedDate":1597950380596,"id":299,"name":"[R2D2 - COVID19] Smoker - amount smoked in pack years"},{"createdBy":"","modifiedBy":"","createdDate":1597948164119,"modifiedDate":1597951093489,"id":306,"name":"[R2D2 - COVID19] Smoking - Meas Value - Status Unkown"},{"createdBy":"","modifiedBy":"","createdDate":1597954647184,"modifiedDate":1597954647185,"id":309,"name":"[R2D2 - COVID19] Smoking  - Meas Value - Passive Smoking"},{"createdBy":"","modifiedBy":"","createdDate":1597719657949,"modifiedDate":1597764521283,"id":290,"name":"[R2D2 - COVID19] Mechanical Ventilation (non-invasive/invasive), Intubation of Respiratory Tract, Ventilator Use - ALL"},{"createdBy":"","modifiedBy":"","createdDate":1598038304697,"modifiedDate":1598038304697,"id":311,"name":"Charybdis - ECMO"},{"createdBy":"","modifiedBy":"","createdDate":1598038444790,"modifiedDate":1598038444790,"id":313,"name":"Cohortdefinition_308 - ECMO"},{"createdBy":"","modifiedBy":"","createdDate":1598745957359,"modifiedDate":1598745957360,"id":315,"name":"COPY OF: [R2D2 - COVID19] INPATIENT VISIT"},{"createdBy":"","modifiedBy":"","createdDate":1599615667177,"modifiedDate":1599615667178,"id":319,"name":"atlascovid19_262_R2D2__CoronaryHeartDisease"},{"createdBy":"","modifiedBy":"","createdDate":1597947663363,"modifiedDate":1597947663364,"id":302,"name":"[R2D2 - COVID19] Smoking - Meas Value - Smoker"},{"createdBy":"","modifiedBy":"","createdDate":1597947847110,"modifiedDate":1597947957843,"id":304,"name":"[R2D2 - COVID19] Smoking - Meas Value - Quitting smoking"}]